{
	"name": "HMG",
	"plugin-id": "Sprite",
	"sid": 512383492291902,
	"isGlobal": false,
	"instanceVariables": [],
	"behaviorTypes": [],
	"effectTypes": [],
	"animations": {
		"items": [
			{
				"frames": [
					{
						"width": 128,
						"height": 119,
						"originX": 0.59375,
						"originY": 0.21008403361344538,
						"originalSource": "",
						"exportFormat": "lossless",
						"exportQuality": 0.8,
						"imageSpriteId": 3121031,
						"useCollisionPoly": true,
						"duration": 1
					}
				],
				"sid": 202993595095551,
				"name": "Animation 1",
				"isLooping": false,
				"isPingPong": false,
				"repeatCount": 1,
				"repeatTo": 0,
				"speed": 5
			}
		],
		"subfolders": []
	}
}